{
    "translation": {
        "start": "Start {{keys}}",
        "stop": "Stop {{keys}}",
        "click_with_timer": "Click with timer",
        "millis": "Milliseconds",
        "second": "Second",
        "settings": "Settings",
        "general": "General",
        "language": "Language",
        "update_available": "Update available",
        "click_stop": "Click has been stopped",
        "click_start": "Clicking is initiated {{delay}} times per second!",
        "click_key_expl_text": "Presses the selected key or keys at specified millisecond intervals when the application is started",
        "attention": "Attention!",
        "not_admin_text": "The application was not run as administrator! This may cause the program not to work in some applications.",
        "delay_error": "The click delay can be a minimum of 1 millisecond.",
        "error_occured": "An error occurred while starting the action! Error: {{err}}",
        "start_up": "Run program at startup",
        "show_notifications": "Show notifications",
        "hold_key": "Hold the key",
        "hold_key_expl_text": "When the application is started, it starts pressing the selected key and keeps it pressed until the application is stopped.",
        "hold_start": "Started holding down the selected key",
        "press_and_hold": "Press and hold key released",
        "dark_mode": "Dark mode",
        "mouse": "Mouse",
        "keyboard": "Keyboard",
        "buttons": "Buttons are",
        "recording": "recording",
        "not_recording": "not recording",
        "not_available_for_now": "Not available for now",
        "shortcut_key": "Shortcut key"
    }
}